HISTORY.md
MANIFEST.in
README.md
setup.cfg
setup.py
cccp/__init__.py
cccp/__version__.py
cccp.egg-info/PKG-INFO
cccp.egg-info/SOURCES.txt
cccp.egg-info/dependency_links.txt
cccp.egg-info/not-zip-safe
cccp.egg-info/requires.txt
cccp.egg-info/top_level.txt