Metadata-Version: 2.1
Name: cccp
Version: 0.0.3
Summary: semi server side rendered html and javascript
Home-page: https://github.com/sloev/cccp
Author: ('sloev',)
Author-email: johannes.valbjorn@gmail.com
License: UNKNOWN
Keywords: cccp serverside server side rendering
Platform: UNKNOWN
Classifier: Development Status :: 2 - Pre-Alpha
Classifier: Intended Audience :: Developers
Classifier: Natural Language :: English
Classifier: Programming Language :: Python :: 2.7
Classifier: Programming Language :: Python :: 3.5
Classifier: Programming Language :: Python :: 3.6
